paginator/__init__.py
paginator/composers/__init__.py
paginator/composers/map.py
paginator/composers/menu.py
paginator/consts.py
paginator/main.py
ptb_menu_pagination-0.2.2.dist-info/LICENSE
ptb_menu_pagination-0.2.2.dist-info/WHEEL
ptb_menu_pagination-0.2.2.dist-info/METADATA
ptb_menu_pagination-0.2.2.dist-info/RECORD
