Metadata-Version: 2.1
Name: ptb-menu-pagination
Version: 0.2.2
Summary: Creates google-like navigation menu using python-telegram-bot wrapper
Home-page: https://github.com/SergSm/ptb-menu-pagination
License: MIT
Keywords: python-telegram-bot,pagination,menu,telegram-bot,telegram-bot-pagination
Author: Smirnov Sergey
Requires-Python: >=3.9,<4.0
Classifier: License :: OSI Approved :: MIT License
Classifier: Programming Language :: Python :: 3
Classifier: Programming Language :: Python :: 3.9
Requires-Dist: python-telegram-bot (>=13.8.1,<14.0.0)
Project-URL: Repository, https://github.com/SergSm/ptb-menu-pagination
